pytest_webstage/__init__.py
pytest_webstage/conf.py
pytest_webstage/plugin.py
pytest_webstage/tools.py
pytest_webstage/webstage.py
pytest_webstage-1.0.0.dist-info/METADATA
pytest_webstage-1.0.0.dist-info/WHEEL
pytest_webstage-1.0.0.dist-info/entry_points.txt
pytest_webstage-1.0.0.dist-info/RECORD
