Metadata-Version: 2.1
Name: pytest-webstage
Version: 1.0.0
Summary: Test web apps with pytest
License: Apache-2.0
Author: thislight
Author-email: l1589002388@gmail.com
Requires-Python: >=3.10,<4.0
Classifier: License :: OSI Approved :: Apache Software License
Classifier: Programming Language :: Python :: 3
Classifier: Programming Language :: Python :: 3.10
Classifier: Programming Language :: Python :: 3.11
Classifier: Programming Language :: Python :: 3.12
Requires-Dist: pydantic (>=2.0,<3.0)
Requires-Dist: pytest (>=7.0,<9.0)
Requires-Dist: selenium (>=4.24.0,<5.0.0)
